stubs/__init__.py
tests/__init__.py
tests/dummy_test.py
wortfilter/Application.py
wortfilter/Filter.py
wortfilter/MainWindow.py
wortfilter/NormalizingFilter.py
wortfilter/__init__.py
wortfilter/__main__.py
wortfilter/ui/MainWindow.ui
wortfilter/ui/__init__.py
wortfilter-0.1.2.dist-info/DESCRIPTION.rst
wortfilter-0.1.2.dist-info/METADATA
wortfilter-0.1.2.dist-info/RECORD
wortfilter-0.1.2.dist-info/WHEEL
wortfilter-0.1.2.dist-info/entry_points.txt
wortfilter-0.1.2.dist-info/metadata.json
wortfilter-0.1.2.dist-info/top_level.txt
